{"0": {"id": "8mt2b", "label": "Textfieldjhgfgh", "inputType": "text", "labelPosition": "text-end", "placeholder": "PLace Holder...trhyhg", "description": "", "validate": {"required": "False", "minLength": "2", "maxLength": "4", "step": "0654"}, "conditional": {"quetion_related": [""], "evaluate": "prueba"}}, "1": {"id": "gc2ebf", "label": "Numberjhgfghjyu", "inputType": "number", "labelPosition": "text-start", "placeholder": "question numberytyut765", "description": "", "validate": {"required": "False", "minLength": "15", "maxLength": "20", "step": "0"}, "conditional": {"quetion_related": "", "evaluate": "prueba"}}}